[
  {
    "chunk_index": 0,
    "start_seconds": 0.0,
    "end_seconds": 90.0,
    "audio_path": "media/runs/2db5ba9b-dce0-4f21-9f56-df21253656b6/chunks/chunk_0000.wav",
    "status": "succeeded",
    "transcript_text": "天上太阳红呀红彤彤哎，心中的太阳是毛泽东哎，他领导我们革命哎，真的翻身当家做主人。一呀一自由呀呀自由啊，真的翻身当家做主人。天上太阳红呀红彤彤哎，心中的太阳是毛泽东哎，他领导我们奋勇前进哎，革命江山一片红哎。一呀一自由呀呀自由啊，革命江山一片红。"
  },
  {
    "chunk_index": 1,
    "start_seconds": 90.0,
    "end_seconds": 180.0,
    "audio_path": "media/runs/2db5ba9b-dce0-4f21-9f56-df21253656b6/chunks/chunk_0001.wav",
    "status": "succeeded",
    "transcript_text": "天上太阳红呀红彤彤哎，心中的太阳是毛泽东哎，他领导我们得解放哎，振起翻身当家做主人。一呀一自由呀呀自由啊，振起翻身当家做主人。天上太阳红呀红彤彤哎，心中的太阳是毛泽东哎，他领导我们奋勇前进哎，革命江山一片红哎。一呀一自由呀呀自由啊，革命江山一片红。"
  },
  {
    "chunk_index": 2,
    "start_seconds": 180.0,
    "end_seconds": 254.491,
    "audio_path": "media/runs/2db5ba9b-dce0-4f21-9f56-df21253656b6/chunks/chunk_0002.wav",
    "status": "succeeded",
    "transcript_text": "天上太阳红呀红彤彤哎，心中的太阳是毛泽东哎，看到我们奋勇前进哎，革命江山一片红哎，嗦罗啦子嗦罗啦子，一样一片红哎。"
  }
]
